classroom_simulation/__init__.py
classroom_simulation/core.py
wf_classroom_simulation-0.0.1.dist-info/LICENSE
wf_classroom_simulation-0.0.1.dist-info/METADATA
wf_classroom_simulation-0.0.1.dist-info/WHEEL
wf_classroom_simulation-0.0.1.dist-info/top_level.txt
wf_classroom_simulation-0.0.1.dist-info/RECORD
